[{"code": "08542", "name": "Thị trấn Thanh Sơn", "type": "Thị trấn"}, {"code": "08563", "name": "Xã Sơn Hùng", "type": "Xã"}, {"code": "08572", "name": "Xã Địch Quả", "type": "Xã"}, {"code": "08575", "name": "Xã Giáp Lai", "type": "Xã"}, {"code": "08581", "name": "Xã Thục Luyện", "type": "Xã"}, {"code": "08584", "name": "Xã Võ Miếu", "type": "Xã"}, {"code": "08587", "name": "Xã Thạch Khoán", "type": "Xã"}, {"code": "08602", "name": "Xã Cự Thắng", "type": "Xã"}, {"code": "08605", "name": "Xã Tất Thắng", "type": "Xã"}, {"code": "08611", "name": "Xã Văn Miếu", "type": "Xã"}, {"code": "08614", "name": "Xã Cự Đồng", "type": "Xã"}, {"code": "08623", "name": "Xã Thắng Sơn", "type": "Xã"}, {"code": "08629", "name": "Xã Tân Minh", "type": "Xã"}, {"code": "08632", "name": "Xã Hương Cần", "type": "Xã"}, {"code": "08635", "name": "Xã Khả Cửu", "type": "Xã"}, {"code": "08638", "name": "Xã Đông Cửu", "type": "Xã"}, {"code": "08641", "name": "Xã Tân Lập", "type": "Xã"}, {"code": "08644", "name": "Xã Yên Lãng", "type": "Xã"}, {"code": "08647", "name": "Xã Yên Lương", "type": "Xã"}, {"code": "08650", "name": "Xã Thượng Cửu", "type": "Xã"}, {"code": "08653", "name": "Xã Lương Nha", "type": "Xã"}, {"code": "08656", "name": "Xã Yên Sơn", "type": "Xã"}, {"code": "08659", "name": "Xã Tinh Nhuệ", "type": "Xã"}]