[{"code": "19012", "name": "Xã Quảng Hợp", "type": "Xã"}, {"code": "19015", "name": "Xã Quảng Kim", "type": "Xã"}, {"code": "19018", "name": "Xã Quảng Đông", "type": "Xã"}, {"code": "19021", "name": "Xã Quảng Phú", "type": "Xã"}, {"code": "19024", "name": "Xã Quảng Châu", "type": "Xã"}, {"code": "19027", "name": "Xã Quảng Thạch", "type": "Xã"}, {"code": "19030", "name": "Xã Quảng Lưu", "type": "Xã"}, {"code": "19033", "name": "Xã Quảng Tùng", "type": "Xã"}, {"code": "19036", "name": "Xã Cảnh Dương", "type": "Xã"}, {"code": "19039", "name": "Xã Quảng Tiến", "type": "Xã"}, {"code": "19042", "name": "Xã Quảng Hưng", "type": "Xã"}, {"code": "19045", "name": "Xã Quảng Xuân", "type": "Xã"}, {"code": "19051", "name": "Xã Liên Trường", "type": "Xã"}, {"code": "19057", "name": "Xã Quảng Phương", "type": "Xã"}, {"code": "19063", "name": "Xã Phù Cảnh", "type": "Xã"}, {"code": "19072", "name": "Xã Quảng Thanh", "type": "Xã"}]