[{"code": "19204", "name": "Xã Trường Sơn", "type": "Xã"}, {"code": "19207", "name": "Thị trấn Quán Hàu", "type": "Thị trấn"}, {"code": "19210", "name": "Xã Vĩnh Ninh", "type": "Xã"}, {"code": "19213", "name": "Xã Võ Ninh", "type": "Xã"}, {"code": "19216", "name": "Xã Hải Ninh", "type": "Xã"}, {"code": "19219", "name": "Xã Hàm Ninh", "type": "Xã"}, {"code": "19222", "name": "Xã Duy Ninh", "type": "Xã"}, {"code": "19225", "name": "Xã Gia Ninh", "type": "Xã"}, {"code": "19228", "name": "Xã Trường Xuân", "type": "Xã"}, {"code": "19231", "name": "Xã Hiền Ninh", "type": "Xã"}, {"code": "19234", "name": "Xã Tân Ninh", "type": "Xã"}, {"code": "19237", "name": "Xã Xuân Ninh", "type": "Xã"}, {"code": "19240", "name": "Xã An Ninh", "type": "Xã"}, {"code": "19243", "name": "Xã Vạn Ninh", "type": "Xã"}]