[{"code": "22651", "name": "Thị trấn Diên Khánh", "type": "Thị trấn"}, {"code": "22654", "name": "Xã Diên Lâm", "type": "Xã"}, {"code": "22657", "name": "Xã Diên Điền", "type": "Xã"}, {"code": "22660", "name": "Xã Xuân Đồng", "type": "Xã"}, {"code": "22663", "name": "Xã Diên Sơn", "type": "Xã"}, {"code": "22669", "name": "Xã Diên Phú", "type": "Xã"}, {"code": "22672", "name": "Xã Diên Thọ", "type": "Xã"}, {"code": "22675", "name": "Xã Diên Phước", "type": "Xã"}, {"code": "22678", "name": "Xã Diên Lạc", "type": "Xã"}, {"code": "22681", "name": "Xã Diên Tân", "type": "Xã"}, {"code": "22684", "name": "Xã Diên Hòa", "type": "Xã"}, {"code": "22687", "name": "Xã Diên Thạnh", "type": "Xã"}, {"code": "22690", "name": "Xã Diên Toàn", "type": "Xã"}, {"code": "22693", "name": "Xã Diên An", "type": "Xã"}, {"code": "22696", "name": "Xã Bình Lộc", "type": "Xã"}, {"code": "22702", "name": "Xã Suối Hiệp", "type": "Xã"}, {"code": "22705", "name": "Xã Suối Tiên", "type": "Xã"}]