[{"code": "27931", "name": "Thị trấn Hậu Nghĩa", "type": "Thị trấn"}, {"code": "27934", "name": "Thị trấn Hiệp Hòa", "type": "Thị trấn"}, {"code": "27937", "name": "Thị trấn Đức Hòa", "type": "Thị trấn"}, {"code": "27940", "name": "Xã Lộc Giang", "type": "Xã"}, {"code": "27943", "name": "Xã An Ninh Đông", "type": "Xã"}, {"code": "27946", "name": "Xã An Ninh Tây", "type": "Xã"}, {"code": "27949", "name": "Xã Tân Mỹ", "type": "Xã"}, {"code": "27952", "name": "Xã Hiệp Hòa", "type": "Xã"}, {"code": "27955", "name": "Xã Đức Lập Thượng", "type": "Xã"}, {"code": "27958", "name": "Xã Đức Lập Hạ", "type": "Xã"}, {"code": "27961", "name": "Xã Tân Phú", "type": "Xã"}, {"code": "27964", "name": "Xã Mỹ Hạnh Bắc", "type": "Xã"}, {"code": "27967", "name": "Xã Đức Hòa Thượng", "type": "Xã"}, {"code": "27970", "name": "Xã Hòa Khánh Tây", "type": "Xã"}, {"code": "27973", "name": "Xã Hòa Khánh Đông", "type": "Xã"}, {"code": "27976", "name": "Xã Mỹ Hạnh Nam", "type": "Xã"}, {"code": "27979", "name": "Xã Hòa Khánh Nam", "type": "Xã"}, {"code": "27982", "name": "Xã Đức Hòa Đông", "type": "Xã"}, {"code": "27985", "name": "Xã Đức Hòa Hạ", "type": "Xã"}, {"code": "27988", "name": "Xã Hựu Thạnh", "type": "Xã"}]