[{"code": "28108", "name": "Thị trấn Cần Đước", "type": "Thị trấn"}, {"code": "28111", "name": "Xã Long Trạch", "type": "Xã"}, {"code": "28114", "name": "Xã Long Khê", "type": "Xã"}, {"code": "28117", "name": "Xã Long Định", "type": "Xã"}, {"code": "28120", "name": "Xã Phước Vân", "type": "Xã"}, {"code": "28123", "name": "Xã Long Hòa", "type": "Xã"}, {"code": "28126", "name": "Xã Long Cang", "type": "Xã"}, {"code": "28129", "name": "Xã Long Sơn", "type": "Xã"}, {"code": "28132", "name": "Xã Tân Trạch", "type": "Xã"}, {"code": "28135", "name": "Xã Mỹ Lệ", "type": "Xã"}, {"code": "28138", "name": "Xã Tân Lân", "type": "Xã"}, {"code": "28141", "name": "Xã Phước Tuy", "type": "Xã"}, {"code": "28144", "name": "Xã Long Hựu Đông", "type": "Xã"}, {"code": "28147", "name": "Xã Tân Ân", "type": "Xã"}, {"code": "28150", "name": "Xã Phước Đông", "type": "Xã"}, {"code": "28153", "name": "Xã Long Hựu Tây", "type": "Xã"}, {"code": "28156", "name": "Xã Tân Chánh", "type": "Xã"}]